{"_id":"gulp-rsync","_rev":"49-945298f58aa88f1c5187748c1f236ba8","name":"gulp-rsync","description":"Rsync tasks for deploying gulp file structures","dist-tags":{"latest":"0.0.9"},"versions":{"0.0.1":{"name":"gulp-rsync","version":"0.0.1","description":"Rsync tasks for deploying gulp file structures","main":"index.js","scripts":{"test":"mocha"},"repository":{"type":"git","url":"git://github.com/jerrysu/gulp-rsync.git"},"keywords":["gulpplugin","rsync","ssh","deploy","deployment"],"author":{"name":"Jerry Su","email":"email@jerrysu.me"},"license":"MIT","bugs":{"url":"https://github.com/jerrysu/gulp-rsync/issues"},"homepage":"https://github.com/jerrysu/gulp-rsync","devDependencies":{"better-assert":"^1.0.1","chai":"^1.9.1","gulp-util":"^3.0.0","lodash.every":"^2.4.1","lodash.isstring":"^2.4.1","mocha":"^1.21.4","through2":"^0.6.1"},"_id":"gulp-rsync@0.0.1","_shasum":"a059a73b06b9794a8595309eb7212f4622e0e595","_from":"./","_npmVersion":"1.4.10","_npmUser":{"name":"jerrysu","email":"email@jerrysu.me"},"maintainers":[{"name":"jerrysu","email":"email@jerrysu.me"}],"dist":{"shasum":"a059a73b06b9794a8595309eb7212f4622e0e595","tarball":"https://registry.npmjs.org/gulp-rsync/-/gulp-rsync-0.0.1.tgz"},"directories":{}},"0.0.2":{"name":"gulp-rsync","version":"0.0.2","description":"Rsync tasks for deploying gulp file structures","main":"index.js","scripts":{"test":"mocha"},"repository":{"type":"git","url":"git://github.com/jerrysu/gulp-rsync.git"},"keywords":["gulpplugin","rsync","ssh","deploy","deployment"],"author":{"name":"Jerry Su","email":"email@jerrysu.me"},"license":"MIT","bugs":{"url":"https://github.com/jerrysu/gulp-rsync/issues"},"homepage":"https://github.com/jerrysu/gulp-rsync","dependencies":{"better-assert":"^1.0.1","lodash.every":"^2.4.1","lodash.isstring":"^2.4.1","gulp-util":"^3.0.0","through2":"^0.6.1"},"devDependencies":{"chai":"^1.9.1","mocha":"^1.21.4"},"_id":"gulp-rsync@0.0.2","_shasum":"56cca6b4b2d3b8e6aee168a45a1a544508967772","_from":".","_npmVersion":"1.4.10","_npmUser":{"name":"jerrysu","email":"email@jerrysu.me"},"maintainers":[{"name":"jerrysu","email":"email@jerrysu.me"}],"dist":{"shasum":"56cca6b4b2d3b8e6aee168a45a1a544508967772","tarball":"https://registry.npmjs.org/gulp-rsync/-/gulp-rsync-0.0.2.tgz"},"directories":{}},"0.0.3":{"name":"gulp-rsync","version":"0.0.3","description":"Rsync tasks for deploying gulp file structures","main":"index.js","scripts":{"test":"mocha"},"repository":{"type":"git","url":"git://github.com/jerrysu/gulp-rsync.git"},"keywords":["gulpplugin","rsync","ssh","deploy","deployment"],"author":{"name":"Jerry Su","email":"email@jerrysu.me"},"license":"MIT","bugs":{"url":"https://github.com/jerrysu/gulp-rsync/issues"},"homepage":"https://github.com/jerrysu/gulp-rsync","dependencies":{"better-assert":"^1.0.1","lodash.every":"^2.4.1","lodash.isstring":"^2.4.1","gulp-util":"^3.0.0","through2":"^0.6.1"},"devDependencies":{"chai":"^1.9.1","mocha":"^1.21.4"},"_id":"gulp-rsync@0.0.3","_shasum":"cadf73eafb6da8613074c8304e31a55d181be779","_from":".","_npmVersion":"1.4.10","_npmUser":{"name":"jerrysu","email":"email@jerrysu.me"},"maintainers":[{"name":"jerrysu","email":"email@jerrysu.me"}],"dist":{"shasum":"cadf73eafb6da8613074c8304e31a55d181be779","tarball":"https://registry.npmjs.org/gulp-rsync/-/gulp-rsync-0.0.3.tgz"},"directories":{}},"0.0.4":{"name":"gulp-rsync","version":"0.0.4","description":"Rsync tasks for deploying gulp file structures","main":"index.js","scripts":{"test":"mocha"},"repository":{"type":"git","url":"git://github.com/jerrysu/gulp-rsync.git"},"keywords":["gulpplugin","rsync","ssh","deploy","deployment"],"author":{"name":"Jerry Su","email":"email@jerrysu.me"},"license":"MIT","bugs":{"url":"https://github.com/jerrysu/gulp-rsync/issues"},"homepage":"https://github.com/jerrysu/gulp-rsync","dependencies":{"better-assert":"^1.0.1","lodash.every":"^2.4.1","lodash.isstring":"^2.4.1","gulp-util":"^3.0.0","through2":"^0.6.1"},"devDependencies":{"chai":"^1.9.1","mocha":"^1.21.4"},"_id":"gulp-rsync@0.0.4","_shasum":"a1db926f7056e016b97edafa05a64fdb722e37f6","_from":".","_npmVersion":"1.4.10","_npmUser":{"name":"jerrysu","email":"email@jerrysu.me"},"maintainers":[{"name":"jerrysu","email":"email@jerrysu.me"}],"dist":{"shasum":"a1db926f7056e016b97edafa05a64fdb722e37f6","tarball":"https://registry.npmjs.org/gulp-rsync/-/gulp-rsync-0.0.4.tgz"},"directories":{}},"0.0.5":{"name":"gulp-rsync","version":"0.0.5","description":"Rsync tasks for deploying gulp file structures","main":"index.js","scripts":{"test":"mocha"},"repository":{"type":"git","url":"git://github.com/jerrysu/gulp-rsync.git"},"keywords":["gulpplugin","rsync","ssh","deploy","deployment"],"author":{"name":"Jerry Su","email":"email@jerrysu.me"},"license":"MIT","bugs":{"url":"https://github.com/jerrysu/gulp-rsync/issues"},"homepage":"https://github.com/jerrysu/gulp-rsync","dependencies":{"better-assert":"^1.0.1","lodash.every":"^2.4.1","lodash.isstring":"^2.4.1","gulp-util":"^3.0.0","through2":"^0.6.1"},"devDependencies":{"chai":"^1.9.1","mocha":"^1.21.4"},"_id":"gulp-rsync@0.0.5","_shasum":"3d3406554155da4c937e0f3fec19be04f3558148","_from":".","_npmVersion":"1.4.10","_npmUser":{"name":"jerrysu","email":"email@jerrysu.me"},"maintainers":[{"name":"jerrysu","email":"email@jerrysu.me"}],"dist":{"shasum":"3d3406554155da4c937e0f3fec19be04f3558148","tarball":"https://registry.npmjs.org/gulp-rsync/-/gulp-rsync-0.0.5.tgz"},"directories":{}},"0.0.6":{"name":"gulp-rsync","version":"0.0.6","description":"Rsync tasks for deploying gulp file structures","main":"index.js","scripts":{"test":"mocha"},"repository":{"type":"git","url":"git://github.com/jerrysu/gulp-rsync.git"},"keywords":["gulpplugin","rsync","ssh","deploy","deployment"],"author":{"name":"Jerry Su","email":"email@jerrysu.me"},"license":"MIT","bugs":{"url":"https://github.com/jerrysu/gulp-rsync/issues"},"homepage":"https://github.com/jerrysu/gulp-rsync","dependencies":{"better-assert":"^1.0.1","lodash.every":"^2.4.1","lodash.isstring":"^2.4.1","gulp-util":"^3.0.0","through2":"^0.6.1"},"devDependencies":{"chai":"^1.9.1","mocha":"^1.21.4"},"gitHead":"a190728ce7c9aada84fb0e433e555f61c8d57617","_id":"gulp-rsync@0.0.6","_shasum":"cc1bad967a887368e666b81cba1c8294f098f82f","_from":".","_npmVersion":"3.8.3","_nodeVersion":"5.10.0","_npmUser":{"name":"ebaskoro","email":"eki@baskoro.org"},"dist":{"shasum":"cc1bad967a887368e666b81cba1c8294f098f82f","tarball":"https://registry.npmjs.org/gulp-rsync/-/gulp-rsync-0.0.6.tgz"},"maintainers":[{"name":"ebaskoro","email":"eki@baskoro.org"},{"name":"jerrysu","email":"email@jerrysu.me"}],"_npmOperationalInternal":{"host":"packages-12-west.internal.npmjs.com","tmp":"tmp/gulp-rsync-0.0.6.tgz_1461193363851_0.9581215819343925"},"directories":{}},"0.0.7":{"name":"gulp-rsync","version":"0.0.7","description":"Rsync tasks for deploying gulp file structures","main":"index.js","scripts":{"test":"mocha"},"repository":{"type":"git","url":"git://github.com/jerrysu/gulp-rsync.git"},"keywords":["gulpplugin","rsync","ssh","deploy","deployment"],"author":{"name":"Jerry Su","email":"email@jerrysu.me"},"license":"MIT","bugs":{"url":"https://github.com/jerrysu/gulp-rsync/issues"},"homepage":"https://github.com/jerrysu/gulp-rsync","dependencies":{"better-assert":"^1.0.1","lodash.every":"^2.4.1","lodash.isstring":"^2.4.1","gulp-util":"^3.0.0","through2":"^0.6.1"},"devDependencies":{"chai":"^1.9.1","mocha":"^1.21.4"},"gitHead":"2adb2e75e82ae9f2b00564dc56c9d6a4fa066c42","_id":"gulp-rsync@0.0.7","_shasum":"745f316892f18bfeeade565ac3889b5a001fe9ba","_from":".","_npmVersion":"3.8.3","_nodeVersion":"5.10.0","_npmUser":{"name":"ebaskoro","email":"eki@baskoro.org"},"dist":{"shasum":"745f316892f18bfeeade565ac3889b5a001fe9ba","tarball":"https://registry.npmjs.org/gulp-rsync/-/gulp-rsync-0.0.7.tgz"},"maintainers":[{"name":"ebaskoro","email":"eki@baskoro.org"},{"name":"jerrysu","email":"email@jerrysu.me"}],"_npmOperationalInternal":{"host":"packages-12-west.internal.npmjs.com","tmp":"tmp/gulp-rsync-0.0.7.tgz_1479042690651_0.9694517760071903"},"directories":{}},"0.0.8":{"name":"gulp-rsync","version":"0.0.8","description":"Rsync tasks for deploying gulp file structures","main":"index.js","scripts":{"test":"mocha"},"repository":{"type":"git","url":"git://github.com/jerrysu/gulp-rsync.git"},"keywords":["gulpplugin","rsync","ssh","deploy","deployment"],"author":{"name":"Jerry Su","email":"email@jerrysu.me"},"license":"MIT","bugs":{"url":"https://github.com/jerrysu/gulp-rsync/issues"},"homepage":"https://github.com/jerrysu/gulp-rsync","dependencies":{"better-assert":"^1.0.1","lodash.every":"^2.4.1","lodash.isstring":"^2.4.1","gulp-util":"^3.0.0","through2":"^0.6.1"},"devDependencies":{"chai":"^1.9.1","mocha":"^1.21.4"},"gitHead":"8b0f7d1ee33e7c557be196b7dbf1d404bb5346b5","_id":"gulp-rsync@0.0.8","_shasum":"b3e64835cd6059a4eb121ad58ff71746b4d898cc","_from":".","_npmVersion":"3.10.10","_nodeVersion":"6.10.1","_npmUser":{"name":"ebaskoro","email":"eki@baskoro.org"},"dist":{"shasum":"b3e64835cd6059a4eb121ad58ff71746b4d898cc","tarball":"https://registry.npmjs.org/gulp-rsync/-/gulp-rsync-0.0.8.tgz"},"maintainers":[{"name":"ebaskoro","email":"eki@baskoro.org"},{"name":"jerrysu","email":"email@jerrysu.me"}],"_npmOperationalInternal":{"host":"s3://npm-registry-packages","tmp":"tmp/gulp-rsync-0.0.8.tgz_1495419039015_0.32563003804534674"},"directories":{}},"0.0.9":{"name":"gulp-rsync","version":"0.0.9","description":"Rsync tasks for deploying gulp file structures","main":"index.js","scripts":{"test":"mocha"},"repository":{"type":"git","url":"git://github.com/jerrysu/gulp-rsync.git"},"keywords":["gulpplugin","rsync","ssh","deploy","deployment"],"author":{"name":"Jerry Su","email":"email@jerrysu.me"},"license":"MIT","bugs":{"url":"https://github.com/jerrysu/gulp-rsync/issues"},"homepage":"https://github.com/jerrysu/gulp-rsync","dependencies":{"better-assert":"^1.0.2","fancy-log":"^1.3.3","lodash.every":"^4.6.0","lodash.isstring":"^4.0.1","plugin-error":"^1.0.1","through2":"^3.0.1"},"devDependencies":{"chai":"^4.2.0","mocha":"^7.1.2"},"gitHead":"61aafa4cb8e4aba7ed3809bb782034b30ceb7d19","_id":"gulp-rsync@0.0.9","_nodeVersion":"10.20.1","_npmVersion":"6.14.4","dist":{"integrity":"sha512-IIJET4qj4+dN5cToRYkRzVFcD5S1LikgvENQu48PmWoznbfzQNBuJ7DhPb5jTzi4YT27fbVX+qaSR2IPlO+rWQ==","shasum":"bb0ce2e407e3bb70287fedb8491773449c88823d","tarball":"https://registry.npmjs.org/gulp-rsync/-/gulp-rsync-0.0.9.tgz","fileCount":6,"unpackedSize":23775,"npm-signature":"-----BEGIN PGP SIGNATURE-----\r\nVersion: OpenPGP.js v3.0.4\r\nComment: https://openpgpjs.org\r\n\r\nwsFcBAEBCAAQBQJewAUeCRA9TVsSAnZWagAA6aUP+gNa1WwFD8oobSb9c7iX\n8MPnqcZ2KcW+GZ4WYkk4teNNd76qezBVtqzLg6BaGINFgedyVXH3JNcPMPKn\nCm30/HiRMQ7Nur7zd44Ot5SaChjGIVBH8cj44FRlwMNhPXiktrvIy1NZIU1V\ncu6ehEik8TymPRsf4YcmjduPmRte2Ff0qNbz0MnIXtq455PyXeDuyQVHMha2\nEnSLCUBJjxgCneRjo/SPfzUwT+HZeS0Z2DcuIU6Yh0kQkG1AliIgnRkQJR40\ndF2DN2FgcMh0iK/3Gj2OcVFvJhlCtRqn4cKCkkBIp3Z1qIVnHi3YZKiM32pn\nmaO56t7ln60jcbx7P9yNJzGXQ4Z0v1FyXYCltUuV4d8sn8gnPn8cZ1vgJDFZ\nR0bGmcYpmqNuAhr813ehlIopdNuJ+DTgQht1DkvJUBkd35W++OwWmdtjGs9c\nuqrvc6dXOqoAwQpUeWdMSf/FY9Mx3L3z/oDKAr2+OjVOIfXoiECfI0DJOPzc\nnbGJrUACwTsOOm3sATTWaNf4t/wNRJJCyA7EGBVIB8Tsi8p3G/99uMmjKYsL\ndO1dVcf+OxqBL0e4DKmg9jkXnymByuNmt5W2eXvZxEJLgDWxnA+GwS0BlvRH\nvTGQd2StYMMSQV/5Olcqi1o45EaYXcnhU0VB5hYLBOh/7oA51fdbMpm6JP7l\nrJN7\r\n=8yyN\r\n-----END PGP SIGNATURE-----\r\n"},"maintainers":[{"name":"ebaskoro","email":"eki@baskoro.org"},{"name":"jerrysu","email":"email@jerrysu.me"}],"_npmUser":{"name":"ebaskoro","email":"eki.baskoro@live.com"},"directories":{},"_npmOperationalInternal":{"host":"s3://npm-registry-packages","tmp":"tmp/gulp-rsync_0.0.9_1589642526018_0.566046663333239"},"_hasShrinkwrap":false}},"readme":"## gulp-rsync\r\n\r\nUse the file transferring and syncing capabilities of `rsync` within your Gulp task. `gulp-rsync` calls `rsync` and offers you a subset of options for an easy setup.\r\n\r\n### Prerequisites\r\n\r\n`rsync` needs to be installed on your machine and must be sitting in your PATH.\r\n\r\n### Installation\r\n\r\n```\r\nnpm install gulp-rsync --save-dev\r\n```\r\n\r\n### Usage\r\n\r\n```js\r\nvar gulp = require('gulp');\r\nvar rsync = require('gulp-rsync');\r\n\r\ngulp.task('deploy', function() {\r\n  return gulp.src('build/**')\r\n    .pipe(rsync({\r\n      root: 'build/',\r\n      hostname: 'example.com',\r\n      destination: 'path/to/site/'\r\n    }));\r\n});\r\n```\r\n\r\nA common parameter set for `rsync` is\r\n\r\n```\r\nrsync -avz ...\r\n```\r\n\r\nThis can be achieved by:\r\n\r\n```js\r\nvar gulp = require('gulp');\r\nvar rsync = require('gulp-rsync');\r\n\r\ngulp.task('deploy', function() {\r\n  gulp.src('build/**')\r\n    .pipe(rsync({\r\n      root: 'build/',\r\n      hostname: 'example.com',\r\n      destination: 'path/to/site/',\r\n      archive: true,\r\n      silent: false,\r\n      compress: true\r\n    }));\r\n});\r\n```\r\n\r\n**Note** that `rsync` does not synchronize your `build/`-directory if you give it a trailing `/`.\r\n\r\n\r\n### rsync OPTIONS\r\n\r\n`rsync-gulp` implements the following options of `rsync`. See the [official documentation](https://rsync.samba.org/documentation.html) for more information.\r\n\r\n```\r\n-a, --archive       archive mode; equals -rlptgoD (no -H,-A,-X)\r\n-c, --checksum      skip based on checksum, not mod-time & size\r\n-d, --dirs          transfer directories without recursing\r\n-e, --rsh=COMMAND   specify the remote shell to use\r\n-n, --dry-run       perform a trial run with no changes made\r\n-r, --recursive     recurse into directories\r\n-t, --times         preserve modification times\r\n-u, --update        skip files that are newer on the receiver\r\n-v, --verbose       increase verbosity\r\n-z, --compress      compress file data during the transfer\r\n--chmod             affect file and/or directory permissions\r\n--delete            delete extraneous files from destination dirs\r\n--exclude=PATTERN   exclude files matching PATTERN\r\n--include=PATTERN   don't exclude files matching PATTERN\r\n--port=PORT         specify double-colon alternate port number\r\n--progress          show progress during transfer\r\n```\r\n\r\n\r\n### Windows users\r\n\r\nWhen you are syncing from Windows to Unix you might encounter permission  errors or issues resulting from these. A reason can be that `rsync` tries to preserve NTFS file attributes in UNIX. This behaviour can be remedied by:\r\n\r\n```js\r\nchmod: \"ugo=rwX\"\r\n```\r\n\r\nSo, if you are running `rsync` on Windows put this option in place.\r\n\r\n### API\r\n\r\n#### `rsync(options)`\r\n\r\n##### `options`\r\n\r\n###### `destination`\r\n\r\nType: `string`, **Required**\r\n\r\nThe destination path. Use `hostname` when using a remote path.\r\n\r\n###### `root`\r\n\r\nType: `string`, Default: `process.cwd()`\r\n\r\nSpecifying a root path changes the path names that are transferred to the\r\ndestination. The paths piped into `rsync` must be within the root path (or the\r\nplugin will yell at you).\r\n\r\n```js\r\ngulp.src('build/js/**']).pipe(rsync({destination: '/tmp'}));\r\n```\r\n\r\nThis will create the directory `build` in `/tmp` as well as the directory `js`\r\nin `/tmp/build`.\r\n\r\n```js\r\ngulp.src('build/js/**']).pipe(rsync({root: 'build', destination: '/tmp'}));\r\n```\r\n\r\nThis will create the directory `js` in `/tmp`.\r\n\r\n###### `hostname`\r\n\r\nType: `string`\r\n\r\nThe hostname of the destination. `rsync` will connect to this hostname using SSH\r\nalong with configuration in `~/.ssh/config` or SSH keys stored in a keychain.\r\n\r\nWhen this is omitted, `rsync` will transfer the content to a local path.\r\n\r\n###### `username`\r\n\r\nType: `string`\r\n\r\nUsed to specify a user for the remote host.\r\n\r\n###### `shell`\r\n\r\nType: `string`, Compares to: `rsync -e`\r\n\r\nTypically, `rsync` is configured to use `ssh` by default, but you may prefer to\r\nuse `rsh` on a local network.\r\n\r\n###### `port`\r\n\r\nType: `integer`\r\n\r\nUsed to specify an SSH port for the remote host. Note: This will override the\r\nshell option and force the use `ssh` in `rsync -e ssh --port=PORT`.\r\n\r\n###### `archive`\r\n\r\nType: `boolean`, Default: `false`, Compares to: `rsync -a`\r\n\r\nIf set to `true`, `rsync` will turn on the archive mode which equals `-rlptgoD`:\r\n\r\n```\r\n-r, --recursive  recurse into directories\r\n-l, --links      copy symlinks as symlinks\r\n-p, --perms      preserve permissions\r\n-t, --times      preserve modification times\r\n-g, --group      preserve group\r\n-o, --owner      preserve owner (super-user only)\r\n-D               same as --devices --specials\r\n--devices        preserve device files (super-user only)\r\n--specials       preserve special files\r\n```\r\n\r\n\r\n###### `dryrun`\r\n\r\nType: `boolean`, Default: `false`, Compares to: `rsync -n`\r\n\r\nIf set to `true`, `rsync` will do everything it does without actually syncing.\r\n\r\n\r\n###### `incremental`\r\n\r\nType: `boolean`, Default: `false`, Compares to: `rsync -c`\r\n\r\nIf set to `true`, `rsync` will make incremental updates only. rsync will use the checksum of every file to determine whether a file needs to be updated. This will add a delay to the transfer, but will minimize the amount of files\r\ntransferred each time.\r\n\r\n\r\n\r\n###### `progress`\r\n\r\nType: `boolean`, Default: `false`, Compares to: `rsync --progress`\r\n\r\nIf set to `true`, the transfer progress for each file will be displayed in the\r\nconsole.\r\n\r\nThis looks like:\r\n\r\n```\r\n[20:49:53] gulp-rsync: Starting rsync to example.com:/var/www/example.com/html/...\r\n[20:49:53] gulp-rsync: favicon.ico\r\n[20:49:53] gulp-rsync:         1150 100%  439.45kB/s    0:00:00 (xfer#1, to-check=12/13)\r\n[20:49:53] gulp-rsync: index.html\r\n[20:49:53] gulp-rsync:         2712 100%  101.86kB/s    0:00:00 (xfer#2, to-check=11/13)\r\n[20:49:53] gulp-rsync: css/style.1afca52f.css\r\n[20:49:53] gulp-rsync:         1445 100%   54.27kB/s    0:00:00 (xfer#3, to-check=9/13)\r\n[20:49:53] gulp-rsync: images/photo1.82515393.jpg\r\n[20:49:53] gulp-rsync:        31878 100%    1.09MB/s    0:00:00 (xfer#7, to-check=3/13)\r\n[20:49:53] gulp-rsync: images/photo2.2a41e1e3.jpg\r\n[20:49:53] gulp-rsync:        76988 100%    2.53MB/s    0:00:00 (xfer#9, to-check=1/13)\r\n[20:49:53] gulp-rsync:  \r\n[20:49:53] gulp-rsync: sent 2401 bytes  received 2820 bytes  10442.00 bytes/sec\r\n[20:49:53] gulp-rsync: total size is 114173  speedup is 57.01\r\n[20:49:53] gulp-rsync: Completed rsync.\r\n```\r\n\r\n###### `relative`\r\n\r\nType: `boolean`, Default: `true`, Compares to: `rsync -R`\r\n\r\nBy default, `gulp-rsync` will transfer all paths relative to the `root` specified.\r\nIf you want to transfer assets from multiple paths to a single destination, you\r\ncan set `relative` to `false`.\r\n\r\n```js\r\ngulp.src(['build/js/**/*.js', 'build/css/**/*.css', 'build/images/**'])\r\n  .pipe(rsync({\r\n    hostname: 'example.cdn',\r\n    destination: '/path/to/all/assets',\r\n    relative: false\r\n  }));\r\n```\r\n\r\nThis will transfer all assets (*.js, *.css, and images) into a single directory.\r\n\r\n###### `emptyDirectories`\r\n\r\nType: `boolean`, Default: `false`, Compares to: `rsync -d`\r\n\r\nIf set to `true`, `rsync` will create empty directories.\r\n\r\n###### `times`\r\n\r\nType: `boolean`, Default: `false`, Compares to: `rsync -t`\r\n\r\nPreserves times of the transferred files.\r\n\r\n###### `compress`\r\n\r\nType: `boolean`, Default: `false`, Compares to: `rsync -z`\r\n\r\nCompresses file data during transfer.\r\n\r\n###### `recursive`\r\n\r\nType: `boolean`, Default: `false`\r\n\r\nIf set to `true`, `rsync` will transfer all files and subdirectories recursively.\r\nThis is not necessary when using glob(s) with `gulp.src()`. However, it can be\r\ncombined with non-globbed paths to transfer all files:\r\n\r\n```\r\ngulp.src(['build/js', 'build/css', 'build/images'])\r\n  .pipe(rsync({\r\n    root: 'build/',\r\n    destination: 'tmp/',\r\n    recursive: true\r\n  }));\r\n```\r\n\r\nThis is the same as:\r\n\r\n```\r\ngulp.src(['build/js/**', 'build/css/**', 'build/images/**'])\r\n  .pipe(rsync({\r\n    root: 'build',\r\n    destination: '/tmp'\r\n  }));\r\n```\r\n\r\nThe difference is that the actual `rsync` command used in the first example is\r\nmuch shorter.\r\n\r\n###### clean\r\n\r\nType: `boolean`, Default: `false`, Compares to: `rsync --delete`\r\n\r\nThis must be used with `archive` or `recursive` set to `true`. If set to `true`, this instructs `rsync` to delete all files and directories that are not in the source paths. **Be careful with this option as it could lead to data loss.**\r\n\r\n###### `chmod`\r\n\r\nType: `string`, Compares to: `rsync --chmod=STRING`\r\n\r\nEnables files or directories matching the pattern(s) provided to be excluded\r\nfrom the transfer. This is probably most useful when `recursive` is set to\r\n`true` since it is typically better to make these exclusions in `gulp.src()`.\r\n\r\n###### `chown`\r\n\r\nType: `string`, Compares to: `rsync --chown=STRING`\r\n\r\nForces all remote files to be owned by the USER:GROUP provided in the string. If GROUP is empty, the trailing colon may be omitted, but if USER is empty, a leading colon must be supplied. If you're running macOS please check your rsync version with `rsync --version`. The default system version, older than 3.1.0, doesn't support this option. You can fix this by installing a recent version from Brew (`brew install homebrew/dupes/rsync`) or MacPorts (`sudo port install rsync`).\r\n\r\n###### `exclude`\r\n\r\nType: `string|Array<string>`, Compares to: `rsync --exclude=PATTERN`\r\n\r\nEnables files or directories matching the pattern(s) provided to be excluded\r\nfrom the transfer. This is probably most useful when `recursive` is set to\r\n`true` since it is typically better to make these exclusions in `gulp.src()`.\r\n\r\n###### `include`\r\n\r\nType: `string|Array<string>`, `rsync --include=PATTERN`\r\n\r\nUsed with `exclude`. This adds exceptions for the exclusions.\r\n\r\nFor example:\r\n\r\n```\r\ngulp.src('build')\r\n  .pipe(rsync({\r\n    root: 'build',\r\n    destination: '/tmp',\r\n    recursive: true,\r\n    exclude: ['*.css', '*.js'],\r\n    include: ['*.min.css', '*.min.js']\r\n  }));\r\n```\r\n\r\nThis will transfer only minified CSS and JS files.\r\n\r\n###### `update`\r\n\r\nType: `boolean`, Default: `false`, Compares to: `rsync -u`\r\n\r\nSkip files that are newer on the receiving end.\r\n\r\n###### `silent`\r\n\r\nType: `boolean`, Default: `false`, Compares to: `rsync --no-v`\r\n\r\nTurns off logging.\r\n\r\n###### `links`\r\n\r\nType: `boolean`, Default: `false`\r\n\r\nEnables creation of symbolic links on the receiving end.\r\n\r\n###### `command`\r\n\r\nType: `boolean`, Default: `false`\r\n\r\nThis is not a `rsync`-option. If set to `true`, `gulp-rsync` shows you the generated `rsync` command in your shell.\r\n\r\n#### License\r\n\r\n> The MIT License (MIT)\r\n>\r\n> Copyright © 2015 Jerry Su, http://jerrysu.me\r\n>\r\n> Permission is hereby granted, free of charge, to any person obtaining a copy of\r\n> this software and associated documentation files (the “Software”), to deal in\r\n> the Software without restriction, including without limitation the rights to\r\n> use, copy, modify, merge, publish, distribute, sublicense, and/or sell copies of\r\n> the Software, and to permit persons to whom the Software is furnished to do so,\r\n> subject to the following conditions:\r\n>\r\n> The above copyright notice and this permission notice shall be included in all\r\n> copies or substantial portions of the Software.\r\n>\r\n> THE SOFTWARE IS PROVIDED “AS IS”, WITHOUT WARRANTY OF ANY KIND, EXPRESS OR\r\n> IMPLIED, INCLUDING BUT NOT LIMITED TO THE WARRANTIES OF MERCHANTABILITY, FITNESS\r\n> FOR A PARTICULAR PURPOSE AND NONINFRINGEMENT. IN NO EVENT SHALL THE AUTHORS OR\r\n> COPYRIGHT HOLDERS BE LIABLE FOR ANY CLAIM, DAMAGES OR OTHER LIABILITY, WHETHER\r\n> IN AN ACTION OF CONTRACT, TORT OR OTHERWISE, ARISING FROM, OUT OF OR IN\r\n> CONNECTION WITH THE SOFTWARE OR THE USE OR OTHER DEALINGS IN THE SOFTWARE.\r\n","maintainers":[{"name":"ebaskoro","email":"eki@baskoro.org"},{"name":"jerrysu","email":"email@jerrysu.me"}],"time":{"modified":"2020-05-16T15:22:08.419Z","created":"2014-08-26T07:01:38.925Z","0.0.1":"2014-08-26T07:01:38.925Z","0.0.2":"2014-08-27T16:42:57.028Z","0.0.3":"2014-09-04T00:25:33.420Z","0.0.4":"2014-09-04T14:07:25.698Z","0.0.5":"2014-12-07T15:45:46.451Z","0.0.6":"2016-04-20T23:02:44.274Z","0.0.7":"2016-11-13T13:11:30.885Z","0.0.8":"2017-05-22T02:10:39.090Z","0.0.9":"2020-05-16T15:22:06.134Z"},"homepage":"https://github.com/jerrysu/gulp-rsync","keywords":["gulpplugin","rsync","ssh","deploy","deployment"],"repository":{"type":"git","url":"git://github.com/jerrysu/gulp-rsync.git"},"author":{"name":"Jerry Su","email":"email@jerrysu.me"},"bugs":{"url":"https://github.com/jerrysu/gulp-rsync/issues"},"license":"MIT","readmeFilename":"README.md","users":{"sexyoung1985":true,"beefchimi":true,"jabbrwcky":true,"etsit":true,"adamlu":true,"pixel-industry":true,"herkulano":true,"poliver":true,"grawl":true,"elussich":true,"skrdv":true,"youngluo":true,"liu48566203":true,"doptrois":true,"muzhen":true,"martvalenzuela":true,"mnew":true,"mattweb":true,"cherenkevich":true,"hpiirainen":true,"tcrowe":true,"landy2014":true,"davidhellmann":true,"paulnordlund":true,"bnu":true,"koster1889":true,"maoxiaoke":true,"pronin.cc":true,"krawster":true,"mskjp":true,"arugalab":true,"vidbmak":true},"_etag":"W/\"0ee13b86132220962ec4cf33e1308035\"","_lastModified":"Sat, 16 May 2020 15:22:09 GMT","_cached":true}